bragly/__init__.py
bragly/__main__.py
bragly/brag.py
bragly/cli.py
bragly/config.py
bragly/persist.py
bragly/config_examples/config-files.ini
bragly/config_examples/config-mongodb.ini
bragly/config_examples/config-reldb.ini
bragly/persistance/__init__.py
bragly/persistance/files.py
bragly/persistance/mongodb.py
bragly/persistance/reldb.py
bragly-0.1.4.dist-info/DESCRIPTION.rst
bragly-0.1.4.dist-info/METADATA
bragly-0.1.4.dist-info/RECORD
bragly-0.1.4.dist-info/WHEEL
bragly-0.1.4.dist-info/entry_points.txt
bragly-0.1.4.dist-info/metadata.json
bragly-0.1.4.dist-info/top_level.txt
