Metadata-Version: 2.0
Name: bragly
Version: 0.1.4
Summary: A small tool to remind yourself of your day-to-day accomplishments
Home-page: http://github.com/huntcsg/bragly
Author: Hunter Senft-Grupp
Author-email: huntcgs@gmail.com
License: MIT
Platform: UNKNOWN
Classifier: Development Status :: 3 - Alpha
Classifier: License :: OSI Approved :: MIT License
Classifier: Operating System :: Microsoft :: Windows :: Windows 7
Classifier: Operating System :: POSIX :: Linux
Classifier: Programming Language :: Python :: 2.7
Classifier: Programming Language :: Python :: 3.4
Classifier: Programming Language :: Python :: 3.5
Classifier: Programming Language :: Python :: Implementation :: CPython
Classifier: Topic :: Software Development :: Libraries :: Python Modules
Requires-Dist: arrow
Requires-Dist: six
